smpljcalc/__init__.py
smpljcalc-1.0.0.dist-info/LICENSE.txt
smpljcalc-1.0.0.dist-info/METADATA
smpljcalc-1.0.0.dist-info/WHEEL
smpljcalc-1.0.0.dist-info/top_level.txt
smpljcalc-1.0.0.dist-info/RECORD
