Metadata-Version: 2.1
Name: smpljcalc
Version: 1.0.0
Summary: A terminal based calculator, dont use
Author: Jil
Author-email: syehpython@email.com
Classifier: Programming Language :: Python :: 3
Classifier: License :: OSI Approved :: MIT License
Classifier: Operating System :: OS Independent
Requires-Python: >=3.9
License-File: LICENSE.txt
Requires-Dist: numpy (>=1.18.0)
Requires-Dist: pandas (>=1.0.0)
Requires-Dist: scikit-learn (>=0.22.0)
